[
  {
    "id": "pthl-gongabu",
    "title": "Gongabu Bus Park Crater",
    "description": "Deep crater near the main bus park exit flooding after every rain, forcing buses to swerve into opposing traffic.",
    "latitude": 27.7323,
    "longitude": 85.3079,
    "district": "Kathmandu",
    "municipality": "Kathmandu",
    "wardNumber": "26",
    "ward": "Kathmandu-26",
    "department": "Department of Roads",
    "severity": "high",
    "status": "reported",
    "upvotes": 42,
    "downvotes": 3,
    "reporterName": "Sita Gurung",
    "reportTime": "2026-01-12T04:30:00.000Z"
  },
  {
    "id": "pthl-patan-south",
    "title": "Patan Ring Road Sinkhole",
    "description": "Fresh sinkhole tearing across two lanes close to the Satdobato underpass.",
    "latitude": 27.6589,
    "longitude": 85.3222,
    "district": "Lalitpur",
    "municipality": "Lalitpur",
    "wardNumber": "14",
    "ward": "Lalitpur-14",
    "department": "Lalitpur Infrastructure Cell",
    "severity": "critical",
    "status": "in_progress",
    "upvotes": 88,
    "downvotes": 6,
    "reporterName": "Prakash Karki",
    "reportTime": "2025-12-28T11:00:00.000Z"
  },
  {
    "id": "pthl-kalanki",
    "title": "Kalanki Flyover Joint",
    "description": "Exposed rebar at the flyover joint making two-wheelers skid; patched last week but reopened yesterday.",
    "latitude": 27.6945,
    "longitude": 85.2821,
    "district": "Kathmandu",
    "municipality": "Kathmandu",
    "wardNumber": "14",
    "ward": "Kathmandu-14",
    "department": "Ring Road Maintenance Unit",
    "severity": "medium",
    "status": "fixed",
    "upvotes": 24,
    "downvotes": 2,
    "reporterName": "Anonymous",
    "reportTime": "2025-11-02T09:15:00.000Z",
    "fixedTime": "2025-11-20T06:00:00.000Z"
  }
]
